current_events_magnifier/CE_magnifier.py
current_events_magnifier/CE_magnifier_test.py
current_events_magnifier/__init__.py
current_events_magnifier/cem_utils.py
current_events_magnifier/normalization.py
current_events_magnifier/plot.py
current_events_magnifier/read_f5c_resquiggle.py
current_events_magnifier/read_tombo_resquiggle.py
current_events_magnifier-0.0.3.4.data/scripts/CE_magnifier.py
current_events_magnifier-0.0.3.4.dist-info/LICENSE
current_events_magnifier-0.0.3.4.dist-info/METADATA
current_events_magnifier-0.0.3.4.dist-info/WHEEL
current_events_magnifier-0.0.3.4.dist-info/top_level.txt
current_events_magnifier-0.0.3.4.dist-info/RECORD
