Metadata-Version: 2.1
Name: current-events-magnifier
Version: 0.0.3.4
Summary: A sample tool designed to visualize the features that distinguish between two groups of ONT data at the site level.                It supports two re-squiggle pipeline(Tombo and f5c).
Home-page: https://github.com/lrslab/current_events_magnifier
Author: GUO Zhihao
Author-email: qhuozhihao@icloud.com
Classifier: Programming Language :: Python :: 3
Classifier: License :: OSI Approved :: MIT License
Classifier: Operating System :: OS Independent
Requires-Python: >=3.7
License-File: LICENSE
Requires-Dist: h5py (==3.8.0)
Requires-Dist: numpy (>=1.23.0)
Requires-Dist: pandas (>=1.1.5)
Requires-Dist: plotnine (>=0.8.0)
Requires-Dist: tqdm (>=4.62.0)
Requires-Dist: pysam (>=0.21.0)
Requires-Dist: pyslow5 (>=1.0.0)
